pp_project_hmv/__init__.py
pp_project_hmv/maths.py
pp_project_hmv-0.4.2.dist-info/LICENSE
pp_project_hmv-0.4.2.dist-info/METADATA
pp_project_hmv-0.4.2.dist-info/WHEEL
pp_project_hmv-0.4.2.dist-info/top_level.txt
pp_project_hmv-0.4.2.dist-info/RECORD
