Metadata-Version: 2.1
Name: pp-project-hmv
Version: 0.4.2
Summary: Example of how to package Python projects
Author-email: Hernando M Vergara <hernybiotec@gmail.com>
License: BSD-3-Clause
Requires-Python: >=3.8.0
License-File: LICENSE
Requires-Dist: numpy
Requires-Dist: pandas
Requires-Dist: setuptools-scm
Provides-Extra: dev
Requires-Dist: pytest ; extra == 'dev'
Requires-Dist: setuptools-scm ; extra == 'dev'
Requires-Dist: flake8 ; extra == 'dev'
Requires-Dist: black ; extra == 'dev'
Requires-Dist: mypy ; extra == 'dev'
Requires-Dist: pre-commit ; extra == 'dev'
